ncrystal_geant4/__init__.py
ncrystal_geant4/cli.py
ncrystal_geant4/cmake/NCrystalGeant4Config.cmake
ncrystal_geant4/cmake/NCrystalGeant4ConfigVersion.cmake
ncrystal_geant4/cmake/include/G4NCrystal/G4NCBias.hh
ncrystal_geant4/cmake/include/G4NCrystal/G4NCInstall.hh
ncrystal_geant4/cmake/include/G4NCrystal/G4NCMatHelper.hh
ncrystal_geant4/cmake/include/G4NCrystal/G4NCrystal.hh
ncrystal_geant4/cmake/src/G4NCBias.cc
ncrystal_geant4/cmake/src/G4NCInstall.cc
ncrystal_geant4/cmake/src/G4NCManager.cc
ncrystal_geant4/cmake/src/G4NCManager.hh
ncrystal_geant4/cmake/src/G4NCMatHelper.cc
ncrystal_geant4/cmake/src/G4NCProcWrapper.cc
ncrystal_geant4/cmake/src/G4NCProcWrapper.hh
ncrystal_geant4-0.1.0.dist-info/licenses/LICENSE
ncrystal_geant4-0.1.0.dist-info/METADATA
ncrystal_geant4-0.1.0.dist-info/WHEEL
ncrystal_geant4-0.1.0.dist-info/entry_points.txt
ncrystal_geant4-0.1.0.dist-info/top_level.txt
ncrystal_geant4-0.1.0.dist-info/RECORD
