Metadata-Version: 2.4
Name: ncrystal-geant4
Version: 0.1.0
Summary: Bindings supporting NCrystal usage in Geant4.
Author: NCrystal developers (Thomas Kittelmann, Xiao Xiao Cai)
License: The Apache 2.0 license is reproduced in the following. See the NOTICE file for
Project-URL: Homepage, https://github.com/mctools/ncrystal-geant4
Project-URL: Bug Tracker, https://github.com/mctools/ncrystal-geant4/issues
Classifier: Programming Language :: Python :: 3
Classifier: License :: OSI Approved :: Apache Software License
License-File: LICENSE
Requires-Dist: ncrystal>=4.1.4
Dynamic: license-file
